<?xml version="1.0" encoding="UTF-8"?>
<objects serializationModel="Studio.02.02.00">
	<object class="AudioFile" id="{c1613d13-66d8-4405-a421-51b49cbf350d}">
		<property name="assetPath">
			<value>Snaps/Snap3.wav</value>
		</property>
		<property name="frequencyInKHz">
			<value>44.0999985</value>
		</property>
		<property name="channelCount">
			<value>2</value>
		</property>
		<property name="length">
			<value>0.1791609977324263</value>
		</property>
		<relationship name="masterAssetFolder">
			<destination>{37f295bd-c32e-48e2-bb8e-4e14b79f7c0d}</destination>
		</relationship>
	</object>
</objects>
